VLMP/VLMP.py
VLMP/__init__.py
VLMP/__main__.py
VLMP/components/__init__.py
VLMP/components/ensembles/NVT.py
VLMP/components/ensembles/NVTlambda.py
VLMP/components/ensembles/__init__.py
VLMP/components/integrators/BBK.py
VLMP/components/integrators/EulerMaruyama.py
VLMP/components/integrators/EulerMaruyamaRigidBody.py
VLMP/components/integrators/EulerMaruyamaRigidBodyPatchesState.py
VLMP/components/integrators/GJF.py
VLMP/components/integrators/MagneticBrownian.py
VLMP/components/integrators/NVE.py
VLMP/components/integrators/__init__.py
VLMP/components/modelExtensions/ACMagneticField.py
VLMP/components/modelExtensions/AFM.py
VLMP/components/modelExtensions/LennardJones.py
VLMP/components/modelExtensions/WCA.py
VLMP/components/modelExtensions/__init__.py
VLMP/components/modelExtensions/absortionSurface.py
VLMP/components/modelExtensions/addBond.py
VLMP/components/modelExtensions/constantForce.py
VLMP/components/modelExtensions/constantForceBetweenCentersOfMass.py
VLMP/components/modelExtensions/constantForceOverCenterOfMass.py
VLMP/components/modelExtensions/constantTorqueBetweenCentersOfMass.py
VLMP/components/modelExtensions/constantTorqueOverCenterOfMass.py
VLMP/components/modelExtensions/constraintCenterOfMassPosition.py
VLMP/components/modelExtensions/constraintParticlesListPositionLambda.py
VLMP/components/modelExtensions/constraintParticlesPosition.py
VLMP/components/modelExtensions/constraintParticlesPositionLambda.py
VLMP/components/modelExtensions/harmonicBondBetweenCentersOfMass.py
VLMP/components/modelExtensions/helixBoundaries.py
VLMP/components/modelExtensions/plates.py
VLMP/components/modelExtensions/sphericalShell.py
VLMP/components/modelExtensions/steric.py
VLMP/components/modelExtensions/surface.py
VLMP/components/modelExtensions/surfaceMaxForce.py
VLMP/components/modelExtensions/uniformField.py
VLMP/components/modelOperations/__init__.py
VLMP/components/modelOperations/alignInertiaMomentAlongVector.py
pyVLMP-1.0.71.dist-info/LICENSE
pyVLMP-1.0.71.dist-info/METADATA
pyVLMP-1.0.71.dist-info/WHEEL
pyVLMP-1.0.71.dist-info/top_level.txt
pyVLMP-1.0.71.dist-info/RECORD
