Metadata-Version: 2.1
Name: pyVLMP
Version: 1.0.71
Summary: Virtual Lab Modeling Platform
Home-page: https://github.com/PabloIbannez/pyGrained
Author-email: Pablo Ibáñez-Freire <p.ibanez.fre@gmail.com>
License: GPLv3
Classifier: Development Status :: 3 - Alpha
Classifier: License :: OSI Approved :: GNU General Public License v3 (GPLv3)
Classifier: Programming Language :: Python :: 3
Classifier: Programming Language :: Python :: 3.6
Classifier: Programming Language :: Python :: 3.7
Classifier: Programming Language :: Python :: 3.8
Classifier: Programming Language :: Python :: 3.9
Requires-Python: >=3.7
License-File: LICENSE
Requires-Dist: jsbeautifier
Requires-Dist: tqdm
Requires-Dist: pyGrained
Requires-Dist: JFIO
Requires-Dist: pyUAMMD
